[
  {
    "player_id": "2599",
    "stats_url": "https://nhlhutbuilder.com/player-stats.php?id=2599",
    "image_url": "https://nhlhutbuilder.com/images/card_art/players/200x285/259923092025060417.jpg",
    "image_alt": "",
    "nationality": "Australia",
    "name": "NATHAN WALKER",
    "overall": "80",
    "card_type": "Check My Game",
    "age": "31",
    "position": "LW",
    "shoots": "LEFT",
    "weight": "187lb",
    "height": "5' 9\"",
    "salary": "$1.0M",
    "starting_average_overall": "78.88",
    "starting_adjusted_overall": "80.40"
  },
  {
    "player_id": "1551",
    "stats_url": "https://nhlhutbuilder.com/player-stats.php?id=1551",
    "image_url": "https://nhlhutbuilder.com/images/card_art/players/200x285/155108092025064017.jpg",
    "image_alt": "",
    "nationality": "Australia",
    "name": "NATHAN WALKER",
    "overall": "77",
    "card_type": "BASE",
    "age": "31",
    "position": "LW",
    "shoots": "LEFT",
    "weight": "187lb",
    "height": "5' 9\"",
    "salary": "$0.7M",
    "starting_average_overall": "76.04",
    "starting_adjusted_overall": "77.60"
  }
]